AI_TTS/__init__.py
AI_TTS-0.0.1.dist-info/LICENSE
AI_TTS-0.0.1.dist-info/METADATA
AI_TTS-0.0.1.dist-info/WHEEL
AI_TTS-0.0.1.dist-info/top_level.txt
AI_TTS-0.0.1.dist-info/RECORD
