Metadata-Version: 2.1
Name: AI-TTS
Version: 0.0.1
Summary: An easy way to use AI TTS
Home-page: https://github.com/WhyFenceCode/AI-Voice
Author: WhyFenceCode
Author-email: whyfencecode@gmail.com
License: MIT
Requires-Python: >=3.8
License-File: LICENSE
